{
  "updated_at": "2026-04-26T16:27:16.176Z",
  "exchange_rate": {
    "usd_to_krw": 1476.67,
    "source": "OpenExchangeRates",
    "last_updated": "2026-04-26T16:27:16.174Z"
  },
  "coins": [
    {
      "coin": "Bitcoin (BTC)",
      "global_price_usd": 78038,
      "global_price_krw": 115236373.46000001,
      "upbit_price": 115981000,
      "kimchi_premium": 0.646173180951812,
      "change_24h": 0.8171381013742494,
      "market_cap": 1562546242997.3477,
      "raw": {
        "global": {
          "usd": 78038,
          "usd_market_cap": 1562546242997.3477,
          "usd_24h_change": 0.8171381013742494
        },
        "upbit": {
          "market": "KRW-BTC",
          "trade_date": "20260426",
          "trade_time": "162714",
          "trade_date_kst": "20260427",
          "trade_time_kst": "012714",
          "trade_timestamp": 1777220834931,
          "opening_price": 115696000,
          "high_price": 116289000,
          "low_price": 115215000,
          "trade_price": 115981000,
          "prev_closing_price": 115696000,
          "change": "RISE",
          "change_price": 285000,
          "change_rate": 0.0024633522,
          "signed_change_price": 285000,
          "signed_change_rate": 0.0024633522,
          "trade_volume": 0.00129331,
          "acc_trade_price": 51139122816.64701,
          "acc_trade_price_24h": 66500971435.22958,
          "acc_trade_volume": 441.43765694,
          "acc_trade_volume_24h": 574.61889549,
          "highest_52_week_price": 179869000,
          "highest_52_week_date": "2025-10-09",
          "lowest_52_week_price": 89000000,
          "lowest_52_week_date": "2026-02-06",
          "timestamp": 1777220835484
        },
        "exchange_rate": 1476.67
      }
    },
    {
      "coin": "Ethereum (ETH)",
      "global_price_usd": 2347.14,
      "global_price_krw": 3465951.2238,
      "upbit_price": 3485000,
      "kimchi_premium": 0.5495973535113832,
      "change_24h": 1.670708862470333,
      "market_cap": 283269899816.0963,
      "raw": {
        "global": {
          "usd": 2347.14,
          "usd_market_cap": 283269899816.0963,
          "usd_24h_change": 1.670708862470333
        },
        "upbit": {
          "market": "KRW-ETH",
          "trade_date": "20260426",
          "trade_time": "162709",
          "trade_date_kst": "20260427",
          "trade_time_kst": "012709",
          "trade_timestamp": 1777220829883,
          "opening_price": 3455000,
          "high_price": 3493000,
          "low_price": 3439000,
          "trade_price": 3485000,
          "prev_closing_price": 3455000,
          "change": "RISE",
          "change_price": 30000,
          "change_rate": 0.008683068,
          "signed_change_price": 30000,
          "signed_change_rate": 0.008683068,
          "trade_volume": 0.0393,
          "acc_trade_price": 39919850644.30177,
          "acc_trade_price_24h": 48151588478.58921,
          "acc_trade_volume": 11513.34870934,
          "acc_trade_volume_24h": 13902.44922854,
          "highest_52_week_price": 6845000,
          "highest_52_week_date": "2025-08-24",
          "lowest_52_week_price": 2496000,
          "lowest_52_week_date": "2025-05-06",
          "timestamp": 1777220829939
        },
        "exchange_rate": 1476.67
      }
    },
    {
      "coin": "XRP (XRP)",
      "global_price_usd": 1.43,
      "global_price_krw": 2111.6381,
      "upbit_price": 2122,
      "kimchi_premium": 0.49070434938637814,
      "change_24h": 0.020552374626013586,
      "market_cap": 88027444650.36882,
      "raw": {
        "global": {
          "usd": 1.43,
          "usd_market_cap": 88027444650.36882,
          "usd_24h_change": 0.020552374626013586
        },
        "upbit": {
          "market": "KRW-XRP",
          "trade_date": "20260426",
          "trade_time": "162709",
          "trade_date_kst": "20260427",
          "trade_time_kst": "012709",
          "trade_timestamp": 1777220829036,
          "opening_price": 2123,
          "high_price": 2128,
          "low_price": 2112,
          "trade_price": 2122,
          "prev_closing_price": 2123,
          "change": "FALL",
          "change_price": 1,
          "change_rate": 0.0004710316,
          "signed_change_price": -1,
          "signed_change_rate": -0.0004710316,
          "trade_volume": 71.58955866,
          "acc_trade_price": 49502269013.07878,
          "acc_trade_price_24h": 68806386438.29979,
          "acc_trade_volume": 23339743.31321272,
          "acc_trade_volume_24h": 32440418.13793527,
          "highest_52_week_price": 4972,
          "highest_52_week_date": "2025-07-18",
          "lowest_52_week_price": 1658,
          "lowest_52_week_date": "2026-02-06",
          "timestamp": 1777220835477
        },
        "exchange_rate": 1476.67
      }
    },
    {
      "coin": "Cardano (ADA)",
      "global_price_usd": 0.252397,
      "global_price_krw": 372.70707799,
      "upbit_price": 375,
      "kimchi_premium": 0.615207530365577,
      "change_24h": 0.8906572743378203,
      "market_cap": 9330687554.114475,
      "raw": {
        "global": {
          "usd": 0.252397,
          "usd_market_cap": 9330687554.114475,
          "usd_24h_change": 0.8906572743378203
        },
        "upbit": {
          "market": "KRW-ADA",
          "trade_date": "20260426",
          "trade_time": "162438",
          "trade_date_kst": "20260427",
          "trade_time_kst": "012438",
          "trade_timestamp": 1777220678701,
          "opening_price": 373,
          "high_price": 378,
          "low_price": 370,
          "trade_price": 375,
          "prev_closing_price": 373,
          "change": "RISE",
          "change_price": 2,
          "change_rate": 0.0053619303,
          "signed_change_price": 2,
          "signed_change_rate": 0.0053619303,
          "trade_volume": 30,
          "acc_trade_price": 4594126232.108198,
          "acc_trade_price_24h": 5957338946.4925995,
          "acc_trade_volume": 12285993.47954949,
          "acc_trade_volume_24h": 15951330.82581764,
          "highest_52_week_price": 1395,
          "highest_52_week_date": "2025-08-14",
          "lowest_52_week_price": 327,
          "lowest_52_week_date": "2026-02-06",
          "timestamp": 1777220832057
        },
        "exchange_rate": 1476.67
      }
    },
    {
      "coin": "Solana (SOL)",
      "global_price_usd": 86.51,
      "global_price_krw": 127746.72170000001,
      "upbit_price": 128500,
      "kimchi_premium": 0.5896654645815391,
      "change_24h": 0.3501707837281496,
      "market_cap": 49819354118.967804,
      "raw": {
        "global": {
          "usd": 86.51,
          "usd_market_cap": 49819354118.967804,
          "usd_24h_change": 0.3501707837281496
        },
        "upbit": {
          "market": "KRW-SOL",
          "trade_date": "20260426",
          "trade_time": "162659",
          "trade_date_kst": "20260427",
          "trade_time_kst": "012659",
          "trade_timestamp": 1777220819551,
          "opening_price": 128500,
          "high_price": 129100,
          "low_price": 127900,
          "trade_price": 128500,
          "prev_closing_price": 128400,
          "change": "RISE",
          "change_price": 100,
          "change_rate": 0.0007788162,
          "signed_change_price": 100,
          "signed_change_rate": 0.0007788162,
          "trade_volume": 0.8614933,
          "acc_trade_price": 12246851069.825888,
          "acc_trade_price_24h": 15345317822.383974,
          "acc_trade_volume": 95367.47097319,
          "acc_trade_volume_24h": 119571.01334344,
          "highest_52_week_price": 350800,
          "highest_52_week_date": "2025-09-18",
          "lowest_52_week_price": 101500,
          "lowest_52_week_date": "2026-02-06",
          "timestamp": 1777220835148
        },
        "exchange_rate": 1476.67
      }
    },
    {
      "coin": "Tether (USDT)",
      "global_price_usd": 1,
      "global_price_krw": 1476.67,
      "upbit_price": 1486,
      "kimchi_premium": 0.6318270161918321,
      "change_24h": -0.007150328556694402,
      "market_cap": 189817646305.91165,
      "raw": {
        "global": {
          "usd": 1,
          "usd_market_cap": 189817646305.91165,
          "usd_24h_change": -0.007150328556694402
        },
        "upbit": {
          "market": "KRW-USDT",
          "trade_date": "20260426",
          "trade_time": "162653",
          "trade_date_kst": "20260427",
          "trade_time_kst": "012653",
          "trade_timestamp": 1777220813034,
          "opening_price": 1490,
          "high_price": 1494,
          "low_price": 1484,
          "trade_price": 1486,
          "prev_closing_price": 1492,
          "change": "FALL",
          "change_price": 6,
          "change_rate": 0.0040214477,
          "signed_change_price": -6,
          "signed_change_rate": -0.0040214477,
          "trade_volume": 178.78532974,
          "acc_trade_price": 46745682901.73496,
          "acc_trade_price_24h": 51274030389.24109,
          "acc_trade_volume": 31388740.27505917,
          "acc_trade_volume_24h": 34425511.28201703,
          "highest_52_week_price": 1655,
          "highest_52_week_date": "2025-10-10",
          "lowest_52_week_price": 1339.5,
          "lowest_52_week_date": "2025-07-11",
          "timestamp": 1777220835460
        },
        "exchange_rate": 1476.67
      }
    },
    {
      "coin": "Shiba Inu (SHIB)",
      "global_price_usd": 0.00000619,
      "global_price_krw": 0.009140587300000001,
      "upbit_price": 0.0092,
      "kimchi_premium": 0.6499877748555494,
      "change_24h": 0.289262728882128,
      "market_cap": 3650333613.047596,
      "raw": {
        "global": {
          "usd": 0.00000619,
          "usd_market_cap": 3650333613.047596,
          "usd_24h_change": 0.289262728882128
        },
        "upbit": {
          "market": "KRW-SHIB",
          "trade_date": "20260426",
          "trade_time": "162631",
          "trade_date_kst": "20260427",
          "trade_time_kst": "012631",
          "trade_timestamp": 1777220791124,
          "opening_price": 0.0092,
          "high_price": 0.00926,
          "low_price": 0.00914,
          "trade_price": 0.0092,
          "prev_closing_price": 0.00921,
          "change": "FALL",
          "change_price": 0.00001,
          "change_rate": 0.0010857763,
          "signed_change_price": -0.00001,
          "signed_change_rate": -0.0010857763,
          "trade_volume": 545000,
          "acc_trade_price": 2085330442.653024,
          "acc_trade_price_24h": 2512402666.0985,
          "acc_trade_volume": 226498815988.4626,
          "acc_trade_volume_24h": 273057032214.43628,
          "highest_52_week_price": 0.02475,
          "highest_52_week_date": "2025-05-12",
          "lowest_52_week_price": 0.00751,
          "lowest_52_week_date": "2026-02-06",
          "timestamp": 1777220822554
        },
        "exchange_rate": 1476.67
      }
    },
    {
      "coin": "Mantle (MNT)",
      "global_price_usd": 0.656598,
      "global_price_krw": 969.5785686600001,
      "upbit_price": 975,
      "kimchi_premium": 0.5591533801631535,
      "change_24h": -0.16035383713303603,
      "market_cap": 2151764480.251474,
      "raw": {
        "global": {
          "usd": 0.656598,
          "usd_market_cap": 2151764480.251474,
          "usd_24h_change": -0.16035383713303603
        },
        "upbit": {
          "market": "KRW-MNT",
          "trade_date": "20260426",
          "trade_time": "154906",
          "trade_date_kst": "20260427",
          "trade_time_kst": "004906",
          "trade_timestamp": 1777218546586,
          "opening_price": 983,
          "high_price": 983,
          "low_price": 967,
          "trade_price": 975,
          "prev_closing_price": 983,
          "change": "FALL",
          "change_price": 8,
          "change_rate": 0.008138352,
          "signed_change_price": -8,
          "signed_change_rate": -0.008138352,
          "trade_volume": 51.2819,
          "acc_trade_price": 362987137.41494787,
          "acc_trade_price_24h": 395124125.7242864,
          "acc_trade_volume": 372000.2924339,
          "acc_trade_volume_24h": 404782.09530601,
          "highest_52_week_price": 4161,
          "highest_52_week_date": "2025-10-09",
          "lowest_52_week_price": 758.2,
          "lowest_52_week_date": "2025-07-04",
          "timestamp": 1777220806902
        },
        "exchange_rate": 1476.67
      }
    }
  ]
}