{
  "TLT": {
    "price": 87.52,
    "dividend_yield": "4.43%",
    "dividend_rate": "N/A",
    "price_change_percent": "0.00%",
    "real_time_yield": "N/A"
  },
  "알트리아": {
    "price": 64.4,
    "dividend_yield": "6.58%",
    "dividend_rate": 4.24,
    "price_change_percent": "0.00%",
    "real_time_yield": "6.58%"
  },
  "버라이즌": {
    "price": 47.39,
    "dividend_yield": "5.97%",
    "dividend_rate": 2.83,
    "price_change_percent": "0.79%",
    "real_time_yield": "5.97%"
  },
  "리얼티 인컴": {
    "price": 63.9,
    "dividend_yield": "5.07%",
    "dividend_rate": 3.24,
    "price_change_percent": "1.28%",
    "real_time_yield": "5.07%"
  },
  "화이자": {
    "price": 27.61,
    "dividend_yield": "6.23%",
    "dividend_rate": 1.72,
    "price_change_percent": "2.07%",
    "real_time_yield": "6.23%"
  },
  "KODEX 금융고배당": {
    "price": 13980,
    "dividend_yield": "N/A",
    "dividend_rate": "N/A",
    "price_change_percent": "0.00%",
    "real_time_yield": "N/A"
  },
  "KODEX 200타겟": {
    "price": 16950,
    "dividend_yield": "N/A",
    "dividend_rate": "N/A",
    "price_change_percent": "0.00%",
    "real_time_yield": "N/A"
  },
  "케이카": {
    "price": 15120,
    "dividend_yield": "7.99%",
    "dividend_rate": 1200,
    "price_change_percent": "0.73%",
    "real_time_yield": "7.94%"
  },
  "하나금융지주": {
    "price": 125800,
    "dividend_yield": "4.47%",
    "dividend_rate": 5464,
    "price_change_percent": "2.95%",
    "real_time_yield": "4.34%"
  },
  "우리금융지주": {
    "price": 37850,
    "dividend_yield": "3.82%",
    "dividend_rate": 1360,
    "price_change_percent": "6.32%",
    "real_time_yield": "3.59%"
  },
  "삼성카드": {
    "price": 60900,
    "dividend_yield": "4.62%",
    "dividend_rate": 2800,
    "price_change_percent": "0.50%",
    "real_time_yield": "4.60%"
  },
  "현대차2우B": {
    "price": 267000,
    "dividend_yield": "4.07%",
    "dividend_rate": 10400,
    "price_change_percent": "4.50%",
    "real_time_yield": "3.90%"
  },
  "SK텔레콤": {
    "price": 75400,
    "dividend_yield": "4.50%",
    "dividend_rate": 3320,
    "price_change_percent": "2.31%",
    "real_time_yield": "4.40%"
  },
  "삼성화재우": {
    "price": 415000,
    "dividend_yield": "4.74%",
    "dividend_rate": 19005,
    "price_change_percent": "3.49%",
    "real_time_yield": "4.58%"
  },
  "BNK 금융지주": {
    "price": 20250,
    "dividend_yield": "6.02%",
    "dividend_rate": 1185,
    "price_change_percent": "2.79%",
    "real_time_yield": "5.85%"
  },
  "NH투자증권우": {
    "price": 24450,
    "dividend_yield": "4.23%",
    "dividend_rate": 1000,
    "price_change_percent": "3.38%",
    "real_time_yield": "4.09%"
  },
  "LG유플러스": {
    "price": 16580,
    "dividend_yield": "4.12%",
    "dividend_rate": 660,
    "price_change_percent": "3.50%",
    "real_time_yield": "3.98%"
  },
  "HD현대": {
    "price": 250000,
    "dividend_yield": "1.47%",
    "dividend_rate": 3600,
    "price_change_percent": "2.04%",
    "real_time_yield": "1.44%"
  },
  "KT": {
    "price": 62700,
    "dividend_yield": "3.95%",
    "dividend_rate": 2400,
    "price_change_percent": "3.29%",
    "real_time_yield": "3.83%"
  },
  "삼성전자": {
    "price": 167800,
    "dividend_yield": "1.37%",
    "dividend_rate": 2264,
    "price_change_percent": "1.21%",
    "real_time_yield": "1.35%"
  },
  "삼성전자우": {
    "price": 116100,
    "dividend_yield": "1.98%",
    "dividend_rate": 2268,
    "price_change_percent": "1.57%",
    "real_time_yield": "1.95%"
  },
  "updated_at": "2026-02-11T07:03:39+00:00"
}